ipcb/__init__.py
ipcb/ep_generator.py
ipcb/evaluate.py
ipcb/model_adm.py
ipcb-0.4.3.dist-info/LICENSE
ipcb-0.4.3.dist-info/METADATA
ipcb-0.4.3.dist-info/WHEEL
ipcb-0.4.3.dist-info/top_level.txt
ipcb-0.4.3.dist-info/RECORD
