Metadata-Version: 2.1
Name: ipcb
Version: 0.4.3
Summary: iPCB utility functions
Author: Luis Liborio
Author-email: lsmliborio@gmail.com
License: MIT
Platform: UNKNOWN
License-File: LICENSE
